mawhrin/__init__.py
mawhrin/__main__.py
mawhrin/comms/__init__.py
mawhrin/comms/base.py
mawhrin/comms/find.py
mawhrin/comms/list.py
mawhrin/comms/make.py
mawhrin/comms/show.py
mawhrin/items/__init__.py
mawhrin/items/book.py
mawhrin/items/note.py
mawhrin/tools/__init__.py
mawhrin/tools/data.py
mawhrin/tools/file.py
mawhrin/tools/path.py
mawhrin-0.2.0.dist-info/METADATA
mawhrin-0.2.0.dist-info/WHEEL
mawhrin-0.2.0.dist-info/entry_points.txt
mawhrin-0.2.0.dist-info/top_level.txt
mawhrin-0.2.0.dist-info/RECORD
