Metadata-Version: 2.1
Name: mawhrin
Version: 0.2.0
Summary: A command-line note file manager in Python.
Author: Stephen Malone
Project-URL: Github, https://github.com/stvmln86/mawhrin
Project-URL: Issues, https://github.com/stvmln86/mawhrin/issues
Project-URL: Changes, https://github.com/stvmln86/mawhrin/blob/main/changes.md
Keywords: cli,notes
Classifier: Development Status :: 3 - Alpha
Classifier: Environment :: Console
Classifier: Intended Audience :: End Users/Desktop
Classifier: License :: OSI Approved :: BSD License
Classifier: Natural Language :: English
Classifier: Programming Language :: Python :: 3.11
Classifier: Topic :: Utilities
Requires-Python: >=3.11
Requires-Dist: click >=8.1
